fitlistreader/__init__.py
fitlistreader/fitintegral.py
fitlistreader/fitintegralcoll.py
fitlistreader/fitlist.py
fitlistreader/fitlistreader.py
fitlistreader/peak.py
fitlistreader-0.1.1.dist-info/LICENSE
fitlistreader-0.1.1.dist-info/METADATA
fitlistreader-0.1.1.dist-info/WHEEL
fitlistreader-0.1.1.dist-info/entry_points.txt
fitlistreader-0.1.1.dist-info/RECORD
