Metadata-Version: 2.1
Name: fitlistreader
Version: 0.1.1
Summary: A package for reading and evaluating fitlist.xml files as generated by hdtv.
License: GNU General Public License v3.0
Author: Markus Muellenmeister
Requires-Python: >=3.8.14,<4.0.0
Classifier: License :: Other/Proprietary License
Classifier: Programming Language :: Python :: 3
Classifier: Programming Language :: Python :: 3.9
Classifier: Programming Language :: Python :: 3.10
Classifier: Programming Language :: Python :: 3.11
Requires-Dist: numpy (>=1.19.4,<2.0.0)
Requires-Dist: scipy (>=1.5.4,<2.0.0)
